MANIFEST.in
README.md
setup.py
calysto_processing/__init__.py
calysto_processing/__main__.py
calysto_processing/kernel.py
calysto_processing.egg-info/PKG-INFO
calysto_processing.egg-info/SOURCES.txt
calysto_processing.egg-info/dependency_links.txt
calysto_processing.egg-info/requires.txt
calysto_processing.egg-info/top_level.txt
calysto_processing/images/logo-32x32.png
calysto_processing/images/logo-64x64.png