Metadata-Version: 1.1
Name: calysto-processing
Version: 2.0.3
Summary: A ProcessingJS kernel for Jupyter
Home-page: https://github.com/Calysto/calysto_processing
Author: Douglas Blank
Author-email: doug.blank@gmail.com
License: UNKNOWN
Platform: UNKNOWN
Classifier: Framework :: IPython
Classifier: License :: OSI Approved :: BSD License
Classifier: Programming Language :: Python :: 3
Classifier: Programming Language :: Python :: 2
Classifier: Topic :: System :: Shells
